LICENSE
MANIFEST.in
Makefile
README.md
pyproject.toml
setup.py
pyplomb/__init__.py
pyplomb/cy_plomb.pyx
pyplomb/octave_filter.py
pyplomb/plomb.py
pyplomb/utils.py
pyplomb.egg-info/PKG-INFO
pyplomb.egg-info/SOURCES.txt
pyplomb.egg-info/dependency_links.txt
pyplomb.egg-info/requires.txt
pyplomb.egg-info/top_level.txt
pyplomb/src/dplomb.c
pyplomb/src/plomb.h
pyplomb/src/splomb.c
pyplomb/src/utils.c
venv/bin/activate_this.py