Metadata-Version: 2.2
Name: pyplomb
Version: 1.5.0
Summary: Python adaptation of MATLAB's Lomb-Scargle periodogram (plomb) in C
Home-page: https://gitlab.com/ArnauMiro/pyplomb
Author: Benet Eiximeno, Arnau Miro
Author-email: Benet Eiximeno <benet.eiximeno@bsc.es>, Arnau Miro <arnau.mirojane@bsc.es>
Maintainer: Arnau Miro
Maintainer-email: Benet Eiximeno <benet.eiximeno@bsc.es>, Arnau Miro <arnau.mirojane@bsc.es>
License: MIT License
Project-URL: Homepage, https://gitlab.com/ArnauMiro/pyplomb
Project-URL: Bug Reports, https://gitlab.com/ArnauMiro/pyplomb/-/issues
Project-URL: Source, https://gitlab.com/ArnauMiro/pyplomb
Keywords: fft,signal processing,signal-processing
Classifier: Development Status :: 5 - Production/Stable
Classifier: Intended Audience :: Science/Research
Classifier: Topic :: Scientific/Engineering
Classifier: License :: OSI Approved :: MIT License
Classifier: Programming Language :: Python :: 3.9
Classifier: Programming Language :: Python :: 3.10
Classifier: Programming Language :: Python :: 3.11
Classifier: Programming Language :: Python :: 3 :: Only
Requires-Python: >=3.9
License-File: LICENSE
Requires-Dist: numpy
Requires-Dist: cython>=3.0.0
Provides-Extra: full
Dynamic: author
Dynamic: home-page
Dynamic: maintainer
